<?xml version="1.0" encoding="UTF-8" standalone="yes"?><xml><records><record><database name="Action.xml" path="file://localhost/Users/School/Desktop/Action.xml">Action.xml</database><source-app name="Papers2" version="2.2.23">Papers2</source-app><rec-number>527</rec-number><ref-type name="Journal Article">17</ref-type><contributors><authors><author><style face="normal" font="default" size="100%">Martin, John Levi</style></author></authors></contributors><titles><title><style face="normal" font="default" size="100%">Life&amp;apos;s a beach but you&amp;apos;re an ant, and other unwelcome news for the sociology of culture</style></title></titles><periodical><abbr-1><style face="normal" font="default" size="100%">Poetics</style></abbr-1><full-title><style face="normal" font="default" size="100%">Poetics</style></full-title></periodical><label>r00527</label><custom3>papers2://publication/uuid/034338CA-E81D-40BA-8C63-E3DF3802D01C</custom3><keywords><keyword><style face="normal" font="default" size="100%">Action</style></keyword><keyword><style face="normal" font="default" size="100%">216</style></keyword></keywords><dates><year><style face="normal" font="default" size="100%">2010</style></year><pub-dates><date><style face="normal" font="default" size="100%"></style></date></pub-dates></dates><pages><style face="normal" font="default" size="100%">229-244</style></pages><volume><style face="normal" font="default" size="100%">38</style></volume><number><style face="normal" font="default" size="100%">2</style></number><electronic-resource-num><style face="normal" font="default" size="100%">10.1016/j.poetic.2009.11.004</style></electronic-resource-num><publisher><style face="normal" font="default" size="100%">Elsevier</style></publisher></record><record><database name="Action.xml" path="file://localhost/Users/School/Desktop/Action.xml">Action.xml</database><source-app name="Papers2" version="2.2.23">Papers2</source-app><rec-number>599</rec-number><ref-type name="Book">6</ref-type><contributors><authors><author><style face="normal" font="default" size="100%">Joas, Hans</style></author></authors></contributors><titles><title><style face="normal" font="default" size="100%">The Creativity of Action, trans</style></title></titles><label>r00599</label><custom3>papers2://publication/uuid/ACFF075C-C228-4A4C-A5ED-C610A5A64FCC</custom3><keywords><keyword><style face="normal" font="default" size="100%">Action</style></keyword><keyword><style face="normal" font="default" size="100%">216</style></keyword></keywords><dates><year><style face="normal" font="default" size="100%">1996</style></year><pub-dates><date><style face="normal" font="default" size="100%"></style></date></pub-dates></dates><publisher><style face="normal" font="default" size="100%">J. Gaines and P. Keast. Cambridge: Polity</style></publisher></record><record><database name="Action.xml" path="file://localhost/Users/School/Desktop/Action.xml">Action.xml</database><source-app name="Papers2" version="2.2.23">Papers2</source-app><rec-number>577</rec-number><ref-type name="Book">6</ref-type><contributors><authors><author><style face="normal" font="default" size="100%">Swidler, Ann</style></author></authors></contributors><titles><title><style face="normal" font="default" size="100%">Talk of love: How culture matters</style></title></titles><label>r00577</label><custom3>papers2://publication/uuid/60FD319A-B4EA-499E-9B1F-730B3D32099D</custom3><keywords><keyword><style face="normal" font="default" size="100%">Action</style></keyword><keyword><style face="normal" font="default" size="100%">216</style></keyword></keywords><dates><year><style face="normal" font="default" size="100%">2003</style></year><pub-dates><date><style face="normal" font="default" size="100%"></style></date></pub-dates></dates><publisher><style face="normal" font="default" size="100%">University of Chicago Press</style></publisher></record><record><database name="Action.xml" path="file://localhost/Users/School/Desktop/Action.xml">Action.xml</database><source-app name="Papers2" version="2.2.23">Papers2</source-app><rec-number>623</rec-number><ref-type name="Conference Paper">47</ref-type><contributors><authors><author><style face="normal" font="default" size="100%">Swidler, Ann</style></author></authors></contributors><titles><title><style face="normal" font="default" size="100%">Comment on Stephen Vaiseys Socrates, Skinner, and Aristotle: Three Ways of Thinking About Culture in Action</style></title></titles><periodical><full-title><style face="normal" font="default" size="100%">Sociological Forum</style></full-title></periodical><label>r00623</label><custom3>papers2://publication/uuid/42B34EB3-8B17-4F52-9AF1-FC13565505B1</custom3><keywords><keyword><style face="normal" font="default" size="100%">Action</style></keyword><keyword><style face="normal" font="default" size="100%">216</style></keyword></keywords><dates><year><style face="normal" font="default" size="100%">2008</style></year><pub-dates><date><style face="normal" font="default" size="100%"></style></date></pub-dates></dates><auth-address><style face="normal" font="default" size="100%">Wiley Online Library</style></auth-address><pages><style face="normal" font="default" size="100%">614-618</style></pages><volume><style face="normal" font="default" size="100%">23</style></volume><number><style face="normal" font="default" size="100%">3</style></number><electronic-resource-num><style face="normal" font="default" size="100%">10.1111/j.1573-7861.2008.00080.x</style></electronic-resource-num></record><record><database name="Action.xml" path="file://localhost/Users/School/Desktop/Action.xml">Action.xml</database><source-app name="Papers2" version="2.2.23">Papers2</source-app><rec-number>6745</rec-number><ref-type name="Journal Article">17</ref-type><contributors><authors><author><style face="normal" font="default" size="100%">Fligstein, Neil</style></author></authors></contributors><titles><title><style face="normal" font="default" size="100%">Social skill and the theory of fields</style></title></titles><periodical><abbr-1><style face="normal" font="default" size="100%">Sociological Theory</style></abbr-1><full-title><style face="normal" font="default" size="100%">Sociological Theory</style></full-title></periodical><label>r06745</label><custom3>papers2://publication/uuid/F3D84CAE-4F1E-420A-883F-D4983F266D5D</custom3><accession-num>7543056310108573634related:wk_KzL9RrmgJ</accession-num><keywords><keyword><style face="normal" font="default" size="100%">Action</style></keyword><keyword><style face="normal" font="default" size="100%">216</style></keyword></keywords><urls><related-urls><url><style face="normal" font="default" size="100%">http://onlinelibrary.wiley.com/doi/10.1111/0735-2751.00132/abstract</style></url></related-urls><pdf-urls><url><style face="normal" font="default" size="100%">file://localhost/Users/School/Dropbox/Papers2/Files/Fligstein%202001.pdf</style></url></pdf-urls></urls><dates><year><style face="normal" font="default" size="100%">2001</style></year><pub-dates><date><style face="normal" font="default" size="100%"></style></date></pub-dates></dates><pages><style face="normal" font="default" size="100%">105-125</style></pages><volume><style face="normal" font="default" size="100%">19</style></volume><number><style face="normal" font="default" size="100%">2</style></number><publisher><style face="normal" font="default" size="100%">Wiley Online Library</style></publisher></record><record><database name="Action.xml" path="file://localhost/Users/School/Desktop/Action.xml">Action.xml</database><source-app name="Papers2" version="2.2.23">Papers2</source-app><rec-number>6539</rec-number><ref-type name="Journal Article">17</ref-type><contributors><authors><author><style face="normal" font="default" size="100%">Parsons, Talcott</style></author></authors></contributors><titles><title><style face="normal" font="default" size="100%">The role of ideas in social action</style></title></titles><periodical><abbr-1><style face="normal" font="default" size="100%">American Sociological Review</style></abbr-1><full-title><style face="normal" font="default" size="100%">American Sociological Review</style></full-title></periodical><label>r06539</label><custom3>papers2://publication/uuid/6E26AC34-350C-42A2-A5D5-73694C10F2E3</custom3><accession-num>7431588715061039660related:LNID5o9OImcJ</accession-num><keywords><keyword><style face="normal" font="default" size="100%">Action</style></keyword><keyword><style face="normal" font="default" size="100%">216</style></keyword></keywords><urls><related-urls><url><style face="normal" font="default" size="100%">http://www.jstor.org/stable/10.2307/2084684</style></url></related-urls><pdf-urls><url><style face="normal" font="default" size="100%">file://localhost/Users/School/Dropbox/Papers2/Files/Parsons%201938.pdf</style></url></pdf-urls></urls><dates><year><style face="normal" font="default" size="100%">1938</style></year><pub-dates><date><style face="normal" font="default" size="100%"></style></date></pub-dates></dates><pages><style face="normal" font="default" size="100%">652-664</style></pages><volume><style face="normal" font="default" size="100%">3</style></volume><number><style face="normal" font="default" size="100%">5</style></number><publisher><style face="normal" font="default" size="100%">JSTOR</style></publisher></record><record><database name="Action.xml" path="file://localhost/Users/School/Desktop/Action.xml">Action.xml</database><source-app name="Papers2" version="2.2.23">Papers2</source-app><rec-number>629</rec-number><ref-type name="Conference Paper">47</ref-type><contributors><authors><author><style face="normal" font="default" size="100%">Vaisey, Stephen</style></author></authors></contributors><titles><title><style face="normal" font="default" size="100%">Reply to Ann Swidler</style></title></titles><periodical><full-title><style face="normal" font="default" size="100%">Sociological Forum</style></full-title></periodical><label>r00629</label><custom3>papers2://publication/uuid/1A66148D-346D-41C2-8FCA-A82272F2B6E8</custom3><keywords><keyword><style face="normal" font="default" size="100%">Action</style></keyword><keyword><style face="normal" font="default" size="100%">216</style></keyword></keywords><dates><year><style face="normal" font="default" size="100%">2008</style></year><pub-dates><date><style face="normal" font="default" size="100%"></style></date></pub-dates></dates><auth-address><style face="normal" font="default" size="100%">Wiley Online Library</style></auth-address><pages><style face="normal" font="default" size="100%">619-622</style></pages><volume><style face="normal" font="default" size="100%">23</style></volume><number><style face="normal" font="default" size="100%">3</style></number><electronic-resource-num><style face="normal" font="default" size="100%">10.1111/j.1573-7861.2008.00081.x</style></electronic-resource-num></record><record><database name="Action.xml" path="file://localhost/Users/School/Desktop/Action.xml">Action.xml</database><source-app name="Papers2" version="2.2.23">Papers2</source-app><rec-number>561</rec-number><ref-type name="Conference Paper">47</ref-type><contributors><authors><author><style face="normal" font="default" size="100%">Mische, Ann</style></author></authors></contributors><titles><title><style face="normal" font="default" size="100%">Projects and possibilities: researching futures in action</style></title></titles><periodical><full-title><style face="normal" font="default" size="100%">Sociological Forum</style></full-title></periodical><label>r00561</label><custom3>papers2://publication/uuid/6F4D0968-F1C0-42A1-84D3-273AE15B9F83</custom3><keywords><keyword><style face="normal" font="default" size="100%">Action</style></keyword><keyword><style face="normal" font="default" size="100%">216</style></keyword></keywords><dates><year><style face="normal" font="default" size="100%">2009</style></year><pub-dates><date><style face="normal" font="default" size="100%"></style></date></pub-dates></dates><auth-address><style face="normal" font="default" size="100%">Wiley Online Library</style></auth-address><pages><style face="normal" font="default" size="100%">694-704</style></pages><volume><style face="normal" font="default" size="100%">24</style></volume><number><style face="normal" font="default" size="100%">3</style></number><electronic-resource-num><style face="normal" font="default" size="100%">10.1111/j.1573-7861.2009.01127.x</style></electronic-resource-num></record><record><database name="Action.xml" path="file://localhost/Users/School/Desktop/Action.xml">Action.xml</database><source-app name="Papers2" version="2.2.23">Papers2</source-app><rec-number>4079</rec-number><ref-type name="Journal Article">17</ref-type><contributors><authors><author><style face="normal" font="default" size="100%">Vaisey, Stephen</style></author><author><style face="normal" font="default" size="100%">Lizardo, Omar</style></author></authors></contributors><titles><title><style face="normal" font="default" size="100%">Can Cultural Worldviews Influence Network Composition?</style></title></titles><periodical><abbr-1><style face="normal" font="default" size="100%">Social Forces</style></abbr-1><full-title><style face="normal" font="default" size="100%">Social Forces</style></full-title></periodical><label>r04079</label><custom3>papers2://publication/uuid/AE7E23EB-2608-445A-AC0A-36FA9EB70B9B</custom3><accession-num>16328174697268258228related:tCUydWBUmeIJ</accession-num><keywords><keyword><style face="normal" font="default" size="100%">Action</style></keyword><keyword><style face="normal" font="default" size="100%">216</style></keyword></keywords><urls><related-urls><url><style face="normal" font="default" size="100%">http://sf.oxfordjournals.org/content/88/4/1595.short</style></url></related-urls><pdf-urls><url><style face="normal" font="default" size="100%">file://localhost/Users/School/Dropbox/Papers2/Files/Vaisey%202010.pdf</style></url></pdf-urls></urls><dates><year><style face="normal" font="default" size="100%">2010</style></year><pub-dates><date><style face="normal" font="default" size="100%"></style></date></pub-dates></dates><pages><style face="normal" font="default" size="100%">1595-1618</style></pages><volume><style face="normal" font="default" size="100%">88</style></volume><number><style face="normal" font="default" size="100%">4</style></number><publisher><style face="normal" font="default" size="100%">Oxford University Press</style></publisher></record><record><database name="Action.xml" path="file://localhost/Users/School/Desktop/Action.xml">Action.xml</database><source-app name="Papers2" version="2.2.23">Papers2</source-app><rec-number>7507</rec-number><ref-type name="Conference Proceedings">10</ref-type><contributors><authors><author><style face="normal" font="default" size="100%">Vaisey, Stephen</style></author></authors></contributors><titles><title><style face="normal" font="default" size="100%">From Contradiction to Coherence: Theory-Building in the Sociology of Culture</style></title></titles><periodical><full-title><style face="normal" font="default" size="100%">Annual Meetings of the American Sociological Association</style></full-title></periodical><label>r07507</label><custom3>papers2://publication/uuid/1FCFEDC5-4FA8-43D3-9757-40555FAD7C94</custom3><accession-num>1373230559098416334related:zqzF9eqxDhMJ</accession-num><keywords><keyword><style face="normal" font="default" size="100%">Action</style></keyword><keyword><style face="normal" font="default" size="100%">216</style></keyword></keywords><urls><related-urls><url><style face="normal" font="default" size="100%">http://stephenvaisey.com/documents/asacontradictiontocoherence.pdf</style></url></related-urls><pdf-urls><url><style face="normal" font="default" size="100%">file://localhost/Users/School/Dropbox/Papers2/Files/Vaisey%202010.pdf</style></url></pdf-urls></urls><dates><year><style face="normal" font="default" size="100%">2010</style></year><pub-dates><date><style face="normal" font="default" size="100%"></style></date></pub-dates></dates><pub-location><style face="normal" font="default" size="100%">Atlanta, GA</style></pub-location></record><record><database name="Action.xml" path="file://localhost/Users/School/Desktop/Action.xml">Action.xml</database><source-app name="Papers2" version="2.2.23">Papers2</source-app><rec-number>637</rec-number><ref-type name="Journal Article">17</ref-type><contributors><authors><author><style face="normal" font="default" size="100%">Vaisey, Stephen</style></author></authors></contributors><titles><title><style face="normal" font="default" size="100%">Socrates, Skinner, and Aristotle: Three Ways of Thinking About Culture in Action1</style></title></titles><periodical><abbr-1><style face="normal" font="default" size="100%">Sociological Forum</style></abbr-1><full-title><style face="normal" font="default" size="100%">Sociological Forum</style></full-title></periodical><label>r00637</label><custom3>papers2://publication/uuid/8857E4F0-9A7C-4FDA-88B2-73F2FC8A4A37</custom3><keywords><keyword><style face="normal" font="default" size="100%">Action</style></keyword><keyword><style face="normal" font="default" size="100%">216</style></keyword></keywords><dates><year><style face="normal" font="default" size="100%">2008</style></year><pub-dates><date><style face="normal" font="default" size="100%"></style></date></pub-dates></dates><auth-address><style face="normal" font="default" size="100%">Wiley Online Library</style></auth-address><pages><style face="normal" font="default" size="100%">603-613</style></pages><volume><style face="normal" font="default" size="100%">23</style></volume><number><style face="normal" font="default" size="100%">3</style></number><electronic-resource-num><style face="normal" font="default" size="100%">10.1111/j.1573-7861.2008.00079.x</style></electronic-resource-num></record><record><database name="Action.xml" path="file://localhost/Users/School/Desktop/Action.xml">Action.xml</database><source-app name="Papers2" version="2.2.23">Papers2</source-app><rec-number>593</rec-number><ref-type name="Book">6</ref-type><contributors><authors><author><style face="normal" font="default" size="100%">Smith, Christian</style></author><author><style face="normal" font="default" size="100%">Denton, Melinda L.</style></author></authors></contributors><titles><title><style face="normal" font="default" size="100%">Soul searching: The religious and spiritual lives of American teenagers</style></title></titles><label>r00593</label><custom3>papers2://publication/uuid/293D8EB7-1B94-4960-8457-ADA4F9375692</custom3><keywords><keyword><style face="normal" font="default" size="100%">Action</style></keyword><keyword><style face="normal" font="default" size="100%">216</style></keyword></keywords><dates><year><style face="normal" font="default" size="100%">2005</style></year><pub-dates><date><style face="normal" font="default" size="100%"></style></date></pub-dates></dates><publisher><style face="normal" font="default" size="100%">Oxford University Press</style></publisher></record><record><database name="Action.xml" path="file://localhost/Users/School/Desktop/Action.xml">Action.xml</database><source-app name="Papers2" version="2.2.23">Papers2</source-app><rec-number>548</rec-number><ref-type name="Journal Article">17</ref-type><contributors><authors><author><style face="normal" font="default" size="100%">Vaisey, Stephen</style></author></authors></contributors><titles><title><style face="normal" font="default" size="100%">Motivation and justification: a dual-process model of culture in action.</style></title></titles><periodical><abbr-1><style face="normal" font="default" size="100%">American Journal of Sociology</style></abbr-1><full-title><style face="normal" font="default" size="100%">American Journal of Sociology</style></full-title></periodical><label>r00548</label><custom3>papers2://publication/uuid/6D6D02EC-4C4F-457A-AEE7-039211E24F06</custom3><keywords><keyword><style face="normal" font="default" size="100%">Action</style></keyword><keyword><style face="normal" font="default" size="100%">216</style></keyword><keyword><style face="normal" font="default" size="100%">Theoretical;Morals</style></keyword><keyword><style face="normal" font="default" size="100%">Humans;Data Collection;Cognitive Science;Culture;Motivation;Cognition;Religion;Models</style></keyword></keywords><dates><year><style face="normal" font="default" size="100%">2009</style></year><pub-dates><date><style face="normal" font="default" size="100%">Jun</style></date></pub-dates></dates><auth-address><style face="normal" font="default" size="100%">Department of Sociology, University of California, 410 Barrows Hall \#1980, Berkeley, California 94720-1980, USA. vaisey\@berkeley.edu</style></auth-address><pages><style face="normal" font="default" size="100%">1675-1715</style></pages><volume><style face="normal" font="default" size="100%">114</style></volume><number><style face="normal" font="default" size="100%">6</style></number><abstract><style face="normal" font="default" size="100%">This article presents a new model of culture in action. Although most sociologists who study culture emphasize its role in post hoc sense making, sociologists of religion and social psychologists tend to focus on the role beliefs play in motivation. The dual-process model integrates justificatory and motivational approaches by distinguishing between &amp;quot;discursive&amp;quot; and &amp;quot;practical&amp;quot; modes of culture and cognition. The author uses panel data from the National Study of Youth and Religion to illustrate the model&amp;apos;s usefulness. Consistent with its predictions, he finds that though respondents cannot articulate clear principles of moral judgment, their choice from a list of moral-cultural scripts strongly predicts later behavior.</style></abstract><month><style face="normal" font="default" size="100%">05</style></month><pub-location><style face="normal" font="default" size="100%">United States</style></pub-location></record><record><database name="Action.xml" path="file://localhost/Users/School/Desktop/Action.xml">Action.xml</database><source-app name="Papers2" version="2.2.23">Papers2</source-app><rec-number>572</rec-number><ref-type name="Journal Article">17</ref-type><contributors><authors><author><style face="normal" font="default" size="100%">Eliasoph, Nina</style></author><author><style face="normal" font="default" size="100%">Lichterman, Paul</style></author></authors></contributors><titles><title><style face="normal" font="default" size="100%">Culture in interaction</style></title></titles><periodical><abbr-1><style face="normal" font="default" size="100%">American Journal of Sociology</style></abbr-1><full-title><style face="normal" font="default" size="100%">American Journal of Sociology</style></full-title></periodical><label>r00572</label><custom3>papers2://publication/uuid/6E7BAD63-6CE5-42CB-9A51-7A657C2E4BD6</custom3><keywords><keyword><style face="normal" font="default" size="100%">Action</style></keyword><keyword><style face="normal" font="default" size="100%">216</style></keyword></keywords><dates><year><style face="normal" font="default" size="100%">2003</style></year><pub-dates><date><style face="normal" font="default" size="100%"></style></date></pub-dates></dates><pages><style face="normal" font="default" size="100%">735-794</style></pages><volume><style face="normal" font="default" size="100%">108</style></volume><number><style face="normal" font="default" size="100%">4</style></number><publisher><style face="normal" font="default" size="100%">JSTOR</style></publisher></record><record><database name="Action.xml" path="file://localhost/Users/School/Desktop/Action.xml">Action.xml</database><source-app name="Papers2" version="2.2.23">Papers2</source-app><rec-number>6806</rec-number><ref-type name="Journal Article">17</ref-type><contributors><authors><author><style face="normal" font="default" size="100%">Hays, S.</style></author></authors></contributors><titles><title><style face="normal" font="default" size="100%">Structure and agency and the sticky problem of culture</style></title></titles><periodical><abbr-1><style face="normal" font="default" size="100%">Sociological Theory</style></abbr-1><full-title><style face="normal" font="default" size="100%">Sociological Theory</style></full-title></periodical><label>r06806</label><custom3>papers2://publication/uuid/62B7C68A-CEF8-432D-8F64-8E0236496244</custom3><accession-num>11320152090487895480related:uDXtfFlCGZ0J</accession-num><keywords><keyword><style face="normal" font="default" size="100%">Action</style></keyword><keyword><style face="normal" font="default" size="100%">216</style></keyword></keywords><urls><related-urls><url><style face="normal" font="default" size="100%">http://www-personal.umich.edu/~lundyj/New%20College%20Class/Readings/Sharon%20Hays_Structure%20and%20Agency%20and%20the%20Sticky%20Problem%20of%20Culture.pdf</style></url></related-urls><pdf-urls><url><style face="normal" font="default" size="100%">file://localhost/Users/School/Dropbox/Papers2/Files/Hays%201994.pdf</style></url></pdf-urls></urls><dates><year><style face="normal" font="default" size="100%">1994</style></year><pub-dates><date><style face="normal" font="default" size="100%"></style></date></pub-dates></dates><pages><style face="normal" font="default" size="100%">57-57</style></pages><volume><style face="normal" font="default" size="100%">12</style></volume><publisher><style face="normal" font="default" size="100%">BLACKWELL PUBLISHERS INC</style></publisher></record><record><database name="Action.xml" path="file://localhost/Users/School/Desktop/Action.xml">Action.xml</database><source-app name="Papers2" version="2.2.23">Papers2</source-app><rec-number>504</rec-number><ref-type name="Journal Article">17</ref-type><contributors><authors><author><style face="normal" font="default" size="100%">Sewell Jr, William H.</style></author></authors></contributors><titles><title><style face="normal" font="default" size="100%">A theory of structure: Duality, agency, and transformation</style></title></titles><periodical><abbr-1><style face="normal" font="default" size="100%">American Journal of Sociology</style></abbr-1><full-title><style face="normal" font="default" size="100%">American Journal of Sociology</style></full-title></periodical><label>r00504</label><custom3>papers2://publication/uuid/A6959553-6D4E-411B-B517-EE6489E7DE22</custom3><keywords><keyword><style face="normal" font="default" size="100%">Action</style></keyword><keyword><style face="normal" font="default" size="100%">216</style></keyword></keywords><dates><year><style face="normal" font="default" size="100%">1992</style></year><pub-dates><date><style face="normal" font="default" size="100%"></style></date></pub-dates></dates><pages><style face="normal" font="default" size="100%">1-29</style></pages><volume><style face="normal" font="default" size="100%">98</style></volume><number><style face="normal" font="default" size="100%">1</style></number><publisher><style face="normal" font="default" size="100%">JSTOR</style></publisher></record></records></xml>