<?xml version="1.0" encoding="UTF-8" standalone="yes"?><xml><records><record><database name="Production.xml" path="file://localhost/Users/School/Dropbox/git/culture-cites/Production/Production.xml">Production.xml</database><source-app name="Papers2" version="2.2.23">Papers2</source-app><rec-number>7820</rec-number><ref-type name="Journal Article">17</ref-type><contributors><authors><author><style face="normal" font="default" size="100%">Griswold, W.</style></author></authors></contributors><titles><title><style face="normal" font="default" size="100%">The fabrication of meaning: Literary interpretation in the United States, Great Britain, and the West Indies</style></title></titles><periodical><abbr-1><style face="normal" font="default" size="100%">AJS</style></abbr-1><full-title><style face="normal" font="default" size="100%">AJS</style></full-title></periodical><label>r07820</label><custom3>papers2://publication/uuid/4E6D3F09-7B30-4B9D-9F60-611E34C18492</custom3><accession-num>9960751184901192209related:EToWqG2yO4oJ</accession-num><keywords><keyword><style face="normal" font="default" size="100%">Production</style></keyword><keyword><style face="normal" font="default" size="100%">216</style></keyword></keywords><urls><related-urls><url><style face="normal" font="default" size="100%">http://www.jstor.org/stable/10.2307/2779997</style></url></related-urls><pdf-urls><url><style face="normal" font="default" size="100%">file://localhost/Users/School/Dropbox/Papers2/Files/Griswold%201987.pdf</style></url></pdf-urls></urls><dates><year><style face="normal" font="default" size="100%">1987</style></year><pub-dates><date><style face="normal" font="default" size="100%"></style></date></pub-dates></dates><pages><style face="normal" font="default" size="100%">1077-1117</style></pages><publisher><style face="normal" font="default" size="100%">JSTOR</style></publisher></record><record><database name="Production.xml" path="file://localhost/Users/School/Dropbox/git/culture-cites/Production/Production.xml">Production.xml</database><source-app name="Papers2" version="2.2.23">Papers2</source-app><rec-number>7821</rec-number><ref-type name="Journal Article">17</ref-type><contributors><authors><author><style face="normal" font="default" size="100%">Rossman, G</style></author><author><style face="normal" font="default" size="100%">Esparza, N</style></author><author><style face="normal" font="default" size="100%">Bonacich, P</style></author></authors></contributors><titles><title><style face="normal" font="default" size="100%">I&amp;apos;d Like to Thank the Academy, Team Spillovers, and Network Centrality</style></title></titles><periodical><abbr-1><style face="normal" font="default" size="100%">American Sociological Review</style></abbr-1><full-title><style face="normal" font="default" size="100%">American Sociological Review</style></full-title></periodical><label>r07821</label><custom3>papers2://publication/uuid/11CFA1FF-3020-4B01-9B78-F3CA9CA6DEA0</custom3><keywords><keyword><style face="normal" font="default" size="100%">Production</style></keyword><keyword><style face="normal" font="default" size="100%">216</style></keyword></keywords><urls><related-urls><url><style face="normal" font="default" size="100%">http://asr.sagepub.com/cgi/doi/10.1177/0003122409359164</style></url></related-urls><pdf-urls><url><style face="normal" font="default" size="100%">file://localhost/Users/School/Dropbox/Papers2/Files/Rossman%202010.pdf</style></url></pdf-urls></urls><dates><year><style face="normal" font="default" size="100%">2010</style></year><pub-dates><date><style face="normal" font="default" size="100%">Apr 05</style></date></pub-dates></dates><pages><style face="normal" font="default" size="100%">31-51</style></pages><volume><style face="normal" font="default" size="100%">75</style></volume><number><style face="normal" font="default" size="100%">1</style></number><electronic-resource-num><style face="normal" font="default" size="100%">10.1177/0003122409359164</style></electronic-resource-num><month><style face="normal" font="default" size="100%">03</style></month><language><style face="normal" font="default" size="100%">English</style></language></record><record><database name="Production.xml" path="file://localhost/Users/School/Dropbox/git/culture-cites/Production/Production.xml">Production.xml</database><source-app name="Papers2" version="2.2.23">Papers2</source-app><rec-number>7890</rec-number><ref-type name="Book">6</ref-type><contributors><authors><author><style face="normal" font="default" size="100%">Wherry, Frederick</style></author></authors></contributors><titles><title><style face="normal" font="default" size="100%">Global Markets and Local Crafts: Thailand and Costa Rica Compared (Themes in Global Social Change)</style></title></titles><label>r07890</label><custom3>papers2://publication/uuid/981CEA0D-5DC0-4194-8674-3B088388E47E</custom3><accession-num>0801887941</accession-num><keywords><keyword><style face="normal" font="default" size="100%">Production</style></keyword><keyword><style face="normal" font="default" size="100%">216</style></keyword></keywords><urls><related-urls><url><style face="normal" font="default" size="100%">http://www.amazon.com/Global-Markets-Local-Crafts-Thailand/dp/0801887941%3FSubscriptionId%3D1V7VTJ4HA4MFT9XBJ1R2%26tag%3Dmekentosjcom-20%26linkCode%3Dxm2%26camp%3D2025%26creative%3D165953%26creativeASIN%3D0801887941</style></url></related-urls></urls><dates><year><style face="normal" font="default" size="100%">2008</style></year><pub-dates><date><style face="normal" font="default" size="100%">Feb 23</style></date></pub-dates></dates><pages><style face="normal" font="default" size="100%">208</style></pages><abstract><style face="normal" font="default" size="100%">Today it is not uncommon to find items in department stores that are hand-crafted in countries like Thailand and Costa Rica. These &amp;quot;traditional&amp;quot; crafts now make up an important part of a global market. They support local and sometimes national economies and help create and solidify cultural identity. But these crafts are not necessarily indigenous. Whereas Thailand markets crafts with a long history and cultural legacy, Costa Rica has created a local handicraft tradition where none was known to exist previously.In Global Markets and Local Crafts, Frederick F. Wherry compares the handicraft industries of Thailand and Costa Rica to show how local cultural industries break into global markets and, conversely, how global markets affect the ways in which artisans understand, adapt, and utilize their cultural traditions. Wherry develops a new framework for studying globalization by considering the phenomenon from the perspective of the supplier instead of the market. Drawing from interviews and extensive fieldwork shadowing artisans and exporters in their daily dealings, Wherry offers a rare account of globalization in motion—and what happens when market negotiations do not proceed as planned. Considering economic and political forces, flows of people and materials, and frames that define cultural and market situations as they play out in the artisan communities of these two countries, Wherry uncovers how authentic folk tradition is capitalized or created. (2008)</style></abstract><isbn><style face="normal" font="default" size="100%">0801887941</style></isbn><month><style face="normal" font="default" size="100%">01</style></month><publisher><style face="normal" font="default" size="100%">The Johns Hopkins University Press</style></publisher><work-type><style face="normal" font="default" size="100%">Hardcover</style></work-type><language><style face="normal" font="default" size="100%">English</style></language></record><record><database name="Production.xml" path="file://localhost/Users/School/Dropbox/git/culture-cites/Production/Production.xml">Production.xml</database><source-app name="Papers2" version="2.2.23">Papers2</source-app><rec-number>2878</rec-number><ref-type name="Journal Article">17</ref-type><contributors><authors><author><style face="normal" font="default" size="100%">Childress, C C</style></author><author><style face="normal" font="default" size="100%">Friedkin, N E</style></author></authors></contributors><titles><title><style face="normal" font="default" size="100%">Cultural Reception and Production: The Social Construction of Meaning in Book Clubs</style></title></titles><periodical><abbr-1><style face="normal" font="default" size="100%">American Sociological Review</style></abbr-1><full-title><style face="normal" font="default" size="100%">American Sociological Review</style></full-title></periodical><label>r02878</label><custom3>papers2://publication/uuid/4DD344A2-A661-41BA-9CCE-65FB57DECF56</custom3><keywords><keyword><style face="normal" font="default" size="100%">Production</style></keyword><keyword><style face="normal" font="default" size="100%">216</style></keyword></keywords><urls><related-urls><url><style face="normal" font="default" size="100%">http://asr.sagepub.com/cgi/doi/10.1177/0003122411428153</style></url></related-urls><pdf-urls><url><style face="normal" font="default" size="100%">file://localhost/Users/School/Dropbox/Papers2/Files/Childress%202012.pdf</style></url></pdf-urls></urls><dates><year><style face="normal" font="default" size="100%">2012</style></year><pub-dates><date><style face="normal" font="default" size="100%">Feb 25</style></date></pub-dates></dates><pages><style face="normal" font="default" size="100%">45-68</style></pages><volume><style face="normal" font="default" size="100%">77</style></volume><number><style face="normal" font="default" size="100%">1</style></number><electronic-resource-num><style face="normal" font="default" size="100%">10.1177/0003122411428153</style></electronic-resource-num><month><style face="normal" font="default" size="100%">01</style></month><language><style face="normal" font="default" size="100%">English</style></language></record><record><database name="Production.xml" path="file://localhost/Users/School/Dropbox/git/culture-cites/Production/Production.xml">Production.xml</database><source-app name="Papers2" version="2.2.23">Papers2</source-app><rec-number>7819</rec-number><ref-type name="Journal Article">17</ref-type><contributors><authors><author><style face="normal" font="default" size="100%">Johnston, Josee</style></author><author><style face="normal" font="default" size="100%">Baumann, Shyon</style></author></authors></contributors><titles><title><style face="normal" font="default" size="100%">Democracy versus Distinction: A Study of Omnivorousness in Gourmet Food Writing</style></title></titles><periodical><abbr-1><style face="normal" font="default" size="100%">American Journal of Sociology</style></abbr-1><full-title><style face="normal" font="default" size="100%">American Journal of Sociology</style></full-title></periodical><label>r07819</label><custom3>papers2://publication/uuid/6F781345-DFC4-40DC-918F-6491A4597E9E</custom3><keywords><keyword><style face="normal" font="default" size="100%">Production</style></keyword><keyword><style face="normal" font="default" size="100%">216</style></keyword></keywords><urls><related-urls><url><style face="normal" font="default" size="100%">http://www.jstor.org/stable/10.1086/518923</style></url></related-urls><pdf-urls><url><style face="normal" font="default" size="100%">file://localhost/Users/School/Dropbox/Papers2/Files/Johnston%202007.pdf</style></url></pdf-urls></urls><dates><year><style face="normal" font="default" size="100%">2007</style></year><pub-dates><date><style face="normal" font="default" size="100%">Jul</style></date></pub-dates></dates><pages><style face="normal" font="default" size="100%">165-204</style></pages><volume><style face="normal" font="default" size="100%">113</style></volume><number><style face="normal" font="default" size="100%">1</style></number><electronic-resource-num><style face="normal" font="default" size="100%">10.1086/518923</style></electronic-resource-num><month><style face="normal" font="default" size="100%">07</style></month><language><style face="normal" font="default" size="100%">English</style></language></record><record><database name="Production.xml" path="file://localhost/Users/School/Dropbox/git/culture-cites/Production/Production.xml">Production.xml</database><source-app name="Papers2" version="2.2.23">Papers2</source-app><rec-number>604</rec-number><ref-type name="Journal Article">17</ref-type><contributors><authors><author><style face="normal" font="default" size="100%">McDonnell, Terrence E.</style></author></authors></contributors><titles><title><style face="normal" font="default" size="100%">Cultural objects as objects: Materiality, urban space, and the interpretation of AIDS campaigns in Accra, Ghana</style></title></titles><periodical><abbr-1><style face="normal" font="default" size="100%">American Journal of Sociology</style></abbr-1><full-title><style face="normal" font="default" size="100%">American Journal of Sociology</style></full-title></periodical><label>r00604</label><custom3>papers2://publication/uuid/415CC361-B647-4162-9666-A1EB4C3F7136</custom3><keywords><keyword><style face="normal" font="default" size="100%">Production</style></keyword><keyword><style face="normal" font="default" size="100%">216</style></keyword></keywords><dates><year><style face="normal" font="default" size="100%">2010</style></year><pub-dates><date><style face="normal" font="default" size="100%"></style></date></pub-dates></dates><pages><style face="normal" font="default" size="100%">1800-1852</style></pages><volume><style face="normal" font="default" size="100%">115</style></volume><number><style face="normal" font="default" size="100%">6</style></number><publisher><style face="normal" font="default" size="100%">University of Chicago Press</style></publisher></record><record><database name="Production.xml" path="file://localhost/Users/School/Dropbox/git/culture-cites/Production/Production.xml">Production.xml</database><source-app name="Papers2" version="2.2.23">Papers2</source-app><rec-number>586</rec-number><ref-type name="Journal Article">17</ref-type><contributors><authors><author><style face="normal" font="default" size="100%">Lizardo, Omar</style></author></authors></contributors><titles><title><style face="normal" font="default" size="100%">How cultural tastes shape personal networks</style></title></titles><periodical><abbr-1><style face="normal" font="default" size="100%">American Sociological Review</style></abbr-1><full-title><style face="normal" font="default" size="100%">American Sociological Review</style></full-title></periodical><label>r00586</label><custom3>papers2://publication/uuid/AFA527F0-BD35-478E-A796-9D06F64B1061</custom3><keywords><keyword><style face="normal" font="default" size="100%">Production</style></keyword><keyword><style face="normal" font="default" size="100%">216</style></keyword></keywords><dates><year><style face="normal" font="default" size="100%">2006</style></year><pub-dates><date><style face="normal" font="default" size="100%"></style></date></pub-dates></dates><pages><style face="normal" font="default" size="100%">778</style></pages><volume><style face="normal" font="default" size="100%">71</style></volume><number><style face="normal" font="default" size="100%">5</style></number><publisher><style face="normal" font="default" size="100%">SAGE Publications</style></publisher></record><record><database name="Production.xml" path="file://localhost/Users/School/Dropbox/git/culture-cites/Production/Production.xml">Production.xml</database><source-app name="Papers2" version="2.2.23">Papers2</source-app><rec-number>632</rec-number><ref-type name="Journal Article">17</ref-type><contributors><authors><author><style face="normal" font="default" size="100%">Binder, Amy J</style></author></authors></contributors><titles><title><style face="normal" font="default" size="100%">Constructing racial rhetoric: Media depictions of harm in heavy metal and rap music</style></title></titles><periodical><abbr-1><style face="normal" font="default" size="100%">American Sociological Review</style></abbr-1><full-title><style face="normal" font="default" size="100%">American Sociological Review</style></full-title></periodical><label>r00632</label><custom3>papers2://publication/uuid/C36CEDC3-AD95-4710-B4F4-FD5CD1CE0D25</custom3><keywords><keyword><style face="normal" font="default" size="100%">Production</style></keyword><keyword><style face="normal" font="default" size="100%">216</style></keyword></keywords><dates><year><style face="normal" font="default" size="100%">1993</style></year><pub-dates><date><style face="normal" font="default" size="100%"></style></date></pub-dates></dates><pages><style face="normal" font="default" size="100%">753-767</style></pages><publisher><style face="normal" font="default" size="100%">JSTOR</style></publisher></record><record><database name="Production.xml" path="file://localhost/Users/School/Dropbox/git/culture-cites/Production/Production.xml">Production.xml</database><source-app name="Papers2" version="2.2.23">Papers2</source-app><rec-number>8844</rec-number><ref-type name="Journal Article">17</ref-type><contributors><authors><author><style face="normal" font="default" size="100%">Horkheimer, M.</style></author><author><style face="normal" font="default" size="100%">Adorno, T.</style></author></authors></contributors><titles><title><style face="normal" font="default" size="100%">The culture industry as mass deception</style></title></titles><periodical><abbr-1><style face="normal" font="default" size="100%">The Dialectic of Enlightenment</style></abbr-1><full-title><style face="normal" font="default" size="100%">The Dialectic of Enlightenment</style></full-title></periodical><label>r08844</label><custom3>papers2://publication/uuid/B4C61540-147B-454E-B120-3604EBE5738A</custom3><accession-num>77219658072189639related:x-oRsd5WEgEJ</accession-num><keywords><keyword><style face="normal" font="default" size="100%">Production</style></keyword><keyword><style face="normal" font="default" size="100%">216</style></keyword></keywords><urls><related-urls><url><style face="normal" font="default" size="100%">http://scholar.google.com/scholar?q=related:x-oRsd5WEgEJ:scholar.google.com/&amp;amp;hl=en&amp;amp;num=30&amp;amp;as_sdt=0,5</style></url></related-urls><pdf-urls><url><style face="normal" font="default" size="100%">file://localhost/Users/School/Dropbox/Papers2/Files/Horkheimer%201979.pdf</style></url></pdf-urls></urls><dates><year><style face="normal" font="default" size="100%">1979</style></year><pub-dates><date><style face="normal" font="default" size="100%"></style></date></pub-dates></dates></record><record><database name="Production.xml" path="file://localhost/Users/School/Dropbox/git/culture-cites/Production/Production.xml">Production.xml</database><source-app name="Papers2" version="2.2.23">Papers2</source-app><rec-number>14065</rec-number><ref-type name="Book">6</ref-type><contributors><authors><author><style face="normal" font="default" size="100%">Liebes, Tamar</style></author><author><style face="normal" font="default" size="100%">Katz, Elihu</style></author></authors></contributors><titles><title><style face="normal" font="default" size="100%">The Export of Meaning</style></title><secondary-title><style face="normal" font="default" size="100%">Cross-Cultural Readings of Dallas</style></secondary-title></titles><label>r14065</label><custom3>papers2://publication/uuid/C8889D00-9E99-4114-ABC8-56FD26B00211</custom3><accession-num>8tleZ84MH1UC</accession-num><keywords><keyword><style face="normal" font="default" size="100%">216</style></keyword><keyword><style face="normal" font="default" size="100%">Production</style></keyword></keywords><urls><related-urls><url><style face="normal" font="default" size="100%">http://books.google.com/books?id=8tleZ84MH1UC&amp;amp;dq=inauthor:liebes+intitle:export+of+meaning&amp;amp;hl=&amp;amp;cd=1&amp;amp;source=gbs_api</style></url></related-urls></urls><dates><year><style face="normal" font="default" size="100%">1993</style></year><pub-dates><date><style face="normal" font="default" size="100%"></style></date></pub-dates></dates><pages><style face="normal" font="default" size="100%">200</style></pages><abstract><style face="normal" font="default" size="100%">In the new paperback edition of this classic text, Liebes and Katz examine how television viewers around the world respond differently to popular television programmes, particularly Dallas. Analszing conversations among viewers in Israel, Japan and the U. S., they show that viewers possess a good deal more critical ability than they are commonly given credit for.</style></abstract><isbn><style face="normal" font="default" size="100%">9780745612959</style></isbn><publisher><style face="normal" font="default" size="100%">Polity</style></publisher><language><style face="normal" font="default" size="100%">English</style></language></record><record><database name="Production.xml" path="file://localhost/Users/School/Dropbox/git/culture-cites/Production/Production.xml">Production.xml</database><source-app name="Papers2" version="2.2.23">Papers2</source-app><rec-number>14068</rec-number><ref-type name="Book">6</ref-type><contributors><authors><author><style face="normal" font="default" size="100%">Radway, Janice A</style></author></authors></contributors><titles><title><style face="normal" font="default" size="100%">Reading the Romance: Women, Patriarchy, and Popular Literature</style></title></titles><label>r14068</label><custom3>papers2://publication/uuid/5A4FA015-4EE0-42B9-8C99-A375A85173D2</custom3><accession-num>17846133317833029174related:NnazH7MzqvcJ</accession-num><keywords><keyword><style face="normal" font="default" size="100%">Production</style></keyword><keyword><style face="normal" font="default" size="100%">216</style></keyword></keywords><urls><related-urls><url><style face="normal" font="default" size="100%">http://www.citeulike.org/group/268/article/200779</style></url></related-urls></urls><dates><year><style face="normal" font="default" size="100%">1991</style></year><pub-dates><date><style face="normal" font="default" size="100%">Nov 01</style></date></pub-dates></dates><pages><style face="normal" font="default" size="100%">306</style></pages><edition><style face="normal" font="default" size="100%">2nd</style></edition><isbn><style face="normal" font="default" size="100%">0807843490</style></isbn><month><style face="normal" font="default" size="100%">11</style></month><publisher><style face="normal" font="default" size="100%">University of North Carolina Press</style></publisher><work-type><style face="normal" font="default" size="100%">Paperback</style></work-type><language><style face="normal" font="default" size="100%">English</style></language></record><record><database name="Production.xml" path="file://localhost/Users/School/Dropbox/git/culture-cites/Production/Production.xml">Production.xml</database><source-app name="Papers2" version="2.2.23">Papers2</source-app><rec-number>14091</rec-number><ref-type name="Book">6</ref-type><contributors><authors><author><style face="normal" font="default" size="100%">Rossman, Gabriel</style></author></authors></contributors><titles><title><style face="normal" font="default" size="100%">Climbing the Charts: What Radio Airplay Tells Us about the Diffusion of Innovation</style></title></titles><label>r14091</label><custom3>papers2://publication/uuid/2581847C-B714-4579-A8D0-5114C755BB9F</custom3><accession-num>566C7A45-6E88-42EE-8694-483931DD797A</accession-num><keywords><keyword><style face="normal" font="default" size="100%">Production</style></keyword><keyword><style face="normal" font="default" size="100%">216</style></keyword></keywords><urls><related-urls><url><style face="normal" font="default" size="100%">http://books.google.com/books?hl=en&amp;amp;lr=&amp;amp;id=E_37GZumy50C&amp;amp;oi=fnd&amp;amp;pg=PP2&amp;amp;dq=rossman+climbing+the+charts&amp;amp;ots=7cWto2jWA6&amp;amp;sig=vOBF3FWLGIp11hFPmyzbLuaKftQ</style></url></related-urls></urls><dates><year><style face="normal" font="default" size="100%">2012</style></year><pub-dates><date><style face="normal" font="default" size="100%">Jul 22</style></date></pub-dates></dates><pages><style face="normal" font="default" size="100%">180</style></pages><abstract><style face="normal" font="default" size="100%">Despite the growth of digital media, traditional FM radio airplay still remains the essential way for musicians to achieve commercial success. Climbing the Charts examines how songs rise, or fail to rise, up the radio airplay charts. Looking at the relationships between record labels, tastemakers, and the public, Gabriel Rossman develops a clear picture of the roles of key players and the gatekeeping mechanisms in the commercial music industry. Along the way, he explores its massive inequalities, debunks many popular misconceptions about radio stations&amp;apos; abilities to dictate hits, and shows how a song diffuses throughout the nation to become a massive success. Contrary to the common belief that Clear Channel sees every sparrow that falls, Rossman demonstrates that corporate radio chains neither micromanage the routine decision of when to start playing a new single nor make top-down decisions to blacklist such politically inconvenient artists as the Dixie Chicks. Neither do stations imitate either ordinary peers or the so-called kingmaker radio stations who are wrongly believed to be able to make or break a single. Instead, Rossman shows that hits spread rapidly across radio because they clearly conform to an identifiable style or genre. Radio stations respond to these songs, and major labels put their money behind them through extensive marketing and promotion efforts, including the illegal yet time-honored practice of payoffs known within the industry as payola. Climbing the Charts provides a fresh take on the music industry and a model for understanding the diffusion of innovation.</style></abstract><isbn><style face="normal" font="default" size="100%">0691148732</style></isbn><month><style face="normal" font="default" size="100%">07</style></month><publisher><style face="normal" font="default" size="100%">Princeton University Press</style></publisher><work-type><style face="normal" font="default" size="100%">Hardcover</style></work-type><language><style face="normal" font="default" size="100%">English</style></language></record><record><database name="Production.xml" path="file://localhost/Users/School/Dropbox/git/culture-cites/Production/Production.xml">Production.xml</database><source-app name="Papers2" version="2.2.23">Papers2</source-app><rec-number>7749</rec-number><ref-type name="Journal Article">17</ref-type><contributors><authors><author><style face="normal" font="default" size="100%">Schudson, Michael</style></author></authors></contributors><titles><title><style face="normal" font="default" size="100%">How culture works: perspectives from media studies on the efficacy of symbols</style></title></titles><periodical><abbr-1><style face="normal" font="default" size="100%">Theory and Society</style></abbr-1><full-title><style face="normal" font="default" size="100%">Theory and society</style></full-title></periodical><label>r07749</label><custom3>papers2://publication/uuid/BDAE127F-3DBF-4535-99E2-59C219EF2364</custom3><accession-num>17926430263327978672related:sPR5oFh5x_gJ</accession-num><keywords><keyword><style face="normal" font="default" size="100%">Production</style></keyword><keyword><style face="normal" font="default" size="100%">216</style></keyword></keywords><urls><related-urls><url><style face="normal" font="default" size="100%">http://www.springerlink.com/index/P2123388258K147V.pdf</style></url></related-urls><pdf-urls><url><style face="normal" font="default" size="100%">file://localhost/Users/School/Dropbox/Papers2/Files/Schudson%201989.pdf</style></url></pdf-urls></urls><dates><year><style face="normal" font="default" size="100%">1989</style></year><pub-dates><date><style face="normal" font="default" size="100%"></style></date></pub-dates></dates><pages><style face="normal" font="default" size="100%">153-180</style></pages><volume><style face="normal" font="default" size="100%">18</style></volume><number><style face="normal" font="default" size="100%">2</style></number><publisher><style face="normal" font="default" size="100%">Springer</style></publisher></record><record><database name="Production.xml" path="file://localhost/Users/School/Dropbox/git/culture-cites/Production/Production.xml">Production.xml</database><source-app name="Papers2" version="2.2.23">Papers2</source-app><rec-number>14052</rec-number><ref-type name="Book">6</ref-type><contributors><authors><author><style face="normal" font="default" size="100%">Bandelj, Nina</style></author><author><style face="normal" font="default" size="100%">Wherry, Frederick</style></author></authors></contributors><titles><title><style face="normal" font="default" size="100%">The Cultural Wealth of Nations</style></title></titles><label>r14052</label><custom3>papers2://publication/uuid/DDB728CE-B920-4056-AF32-631D11828014</custom3><accession-num>rheclfcXGmsC</accession-num><keywords><keyword><style face="normal" font="default" size="100%">Production</style></keyword><keyword><style face="normal" font="default" size="100%">216</style></keyword></keywords><urls><related-urls><url><style face="normal" font="default" size="100%">http://books.google.com/books?id=rheclfcXGmsC&amp;amp;pg=PA13&amp;amp;dq=inauthor:wherry+intitle:the+cultural+wealth+of+nation&amp;amp;hl=&amp;amp;cd=1&amp;amp;source=gbs_api</style></url></related-urls></urls><dates><year><style face="normal" font="default" size="100%">2011</style></year><pub-dates><date><style face="normal" font="default" size="100%">Jul 25</style></date></pub-dates></dates><pages><style face="normal" font="default" size="100%">281</style></pages><abstract><style face="normal" font="default" size="100%">This book advances a cultural perspective on economic development to show that economic success can result from the symbolic resources that nations, regions and communities have at their disposal.</style></abstract><isbn><style face="normal" font="default" size="100%">9780804776455</style></isbn><month><style face="normal" font="default" size="100%">07</style></month><publisher><style face="normal" font="default" size="100%">Stanford Univ Pr</style></publisher><language><style face="normal" font="default" size="100%">English</style></language></record></records></xml>